setup.py
scalr_client_core/__init__.py
scalr_client_core/api.py
scalr_client_core/constant.py
scalr_client_core/exception.py
scalr_client_core/util.py
scalr_client_core/version.py
scalr_client_core.egg-info/PKG-INFO
scalr_client_core.egg-info/SOURCES.txt
scalr_client_core.egg-info/dependency_links.txt
scalr_client_core.egg-info/requires.txt
scalr_client_core.egg-info/top_level.txt
scalr_client_core/test/__init__.py
scalr_client_core/test/test_api.py
scalr_client_core/test/util.py
scalr_client_core/test/test_data/Error.xml
scalr_client_core/test/test_data/FarmGetDetails.xml
scalr_client_core/test/test_data/FarmUpdateRole.xml