Metadata-Version: 1.0
Name: scalr-client-core
Version: 0.1.1
Summary: Low-level client library for the Scalr API
Home-page: http://www.scalr.com
Author: Thomas Orozco
Author-email: thomas@scalr.com
License: Proprietary
Platform: UNKNOWN
